{
  "users": [
    {
      "username": "Ryan DeVault",
      "email": "boardgamegeek@games.net",
      "id": 1
    }
  ],
  "userGames": [
    {
      "id": 2,
      "gameId": "E5TYKwLTf0",
      "userId": 1,
      "gameStateId": 1
    },
    {
      "id": 3,
      "gameId": "IiVHZAZhNi",
      "userId": 1,
      "gameStateId": 1
    },
    {
      "gameId": "i5Oqu5VZgP",
      "userId": 1,
      "gameStateId": 1,
      "id": 6
    },
    {
      "gameId": "RLlDWHh7hR",
      "userId": 1,
      "gameStateId": 1,
      "id": 7
    },
    {
      "gameId": "kPDxpJZ8PD",
      "userId": 1,
      "gameStateId": 1,
      "id": 8
    }
  ],
  "gameStates": [
    {
      "id": 1,
      "state": "Owned & Played"
    },
    {
      "id": 2,
      "state": "Owned & Not Played"
    },
    {
      "id": 3,
      "state": "Wishlisted & Played"
    },
    {
      "id": 4,
      "state": "Wishlisted & Not Played"
    }
  ]
}